src/mips32.v
`timescale 1ns/1ps

module mips32(
    input clk1,
    input clk2
);

    //-----------------------------
    // Program Counter
    //-----------------------------
    reg [31:0] PC;

    //-----------------------------
    // IF/ID Pipeline Registers
    //-----------------------------
    reg [31:0] IF_ID_IR;
    reg [31:0] IF_ID_NPC;

    //-----------------------------
    // ID/EX Pipeline Registers
    //-----------------------------
    reg [31:0] ID_EX_IR;
    reg [31:0] ID_EX_NPC;
    reg [31:0] ID_EX_A;
    reg [31:0] ID_EX_B;
    reg [31:0] ID_EX_IMM;
    reg [2:0]  ID_EX_type;

    //-----------------------------
    // EX/MEM Pipeline Registers
    //-----------------------------
    reg [31:0] EX_MEM_IR;
    reg [31:0] EX_MEM_ALUOut;
    reg [31:0] EX_MEM_B;
    reg [2:0]  EX_MEM_type;
    reg        EX_MEM_cond;

    //-----------------------------
    // MEM/WB Pipeline Registers
    //-----------------------------
    reg [31:0] MEM_WB_IR;
    reg [31:0] MEM_WB_ALUOut;
    reg [31:0] MEM_WB_LMD;
    reg [2:0]  MEM_WB_type;

    //-----------------------------
    // Register File
    //-----------------------------
    reg [31:0] Reg [0:31];

    //-----------------------------
    // Main Memory
    //-----------------------------
    reg [31:0] Mem [0:1023];

    //-----------------------------
    // Instruction Types
    //-----------------------------
    parameter RR_ALU = 3'b000,
              RM_ALU = 3'b001,
              LOAD   = 3'b010,
              STORE  = 3'b011,
              BRANCH = 3'b100,
              HALT   = 3'b101;

    //-----------------------------
    // Opcodes
    //-----------------------------
    parameter ADD   = 6'b000000,
              SUB   = 6'b000001,
              ANDD  = 6'b000010,
              ORR   = 6'b000011,
              SLT   = 6'b000100,
              MUL   = 6'b000101,

              HLT   = 6'b111111,

              LW    = 6'b001000,
              SW    = 6'b001001,

              ADDI  = 6'b001010,
              SUBI  = 6'b001011,
              SLTI  = 6'b001100,

              BNEQZ = 6'b001101,
              BEQZ  = 6'b001110;
              
    reg halted;
    reg taken_branch;

    integer i;

    initial
    begin
        PC = 0;
        halted = 0;
        taken_branch = 0;

        IF_ID_IR = 0;
        IF_ID_NPC = 0;

        ID_EX_IR = 0;
        ID_EX_NPC = 0;
        ID_EX_A = 0;
        ID_EX_B = 0;
        ID_EX_IMM = 0;
        ID_EX_type = 0;

        EX_MEM_IR = 0;
        EX_MEM_ALUOut = 0;
        EX_MEM_B = 0;
        EX_MEM_type = 0;
        EX_MEM_cond = 0;

        MEM_WB_IR = 0;
        MEM_WB_ALUOut = 0;
        MEM_WB_LMD = 0;
        MEM_WB_type = 0;

        for(i = 0; i < 32; i = i + 1)
            Reg[i] = 0;

        for(i = 0; i < 1024; i = i + 1)
            Mem[i] = 0;
    end

    //---------------------------------------------------------
    // 1. INSTRUCTION FETCH (IF) STAGE
    //---------------------------------------------------------
    always @(posedge clk1)
    begin
        if (!halted)
        begin
            // Branch taken by the instruction currently in EX/MEM
            if (((EX_MEM_IR[31:26] == BEQZ)  && EX_MEM_cond) ||
                ((EX_MEM_IR[31:26] == BNEQZ) && !EX_MEM_cond))
            begin
                // Fetch first instruction from branch target
                IF_ID_IR  <= #2 Mem[EX_MEM_ALUOut];
                IF_ID_NPC <= #2 EX_MEM_ALUOut + 1;

                // Update PC to next sequential instruction
                PC <= #2 EX_MEM_ALUOut + 1;

                // Inform later stages to squash the wrong-path instruction
                taken_branch <= #2 1'b1;
            end
            else
            begin
                // Normal sequential fetch
                IF_ID_IR  <= #2 Mem[PC];
                IF_ID_NPC <= #2 PC + 1;

                // Increment PC
                PC <= #2 PC + 1;
                
                // Clear the branch flag so normal execution resumes after squashing
                taken_branch <= #2 1'b0;
            end
        end
    end

    //---------------------------------------------------------
    // 2. INSTRUCTION DECODE (ID) STAGE
    //---------------------------------------------------------
    always @(posedge clk2)
    begin
        if (!halted)
        begin
            if(IF_ID_IR[25:21] == 0)
                ID_EX_A <= #2 0;
            else
                ID_EX_A <= #2 Reg[IF_ID_IR[25:21]];

            if(IF_ID_IR[20:16] == 0)
                ID_EX_B <= #2 0;
            else
                ID_EX_B <= #2 Reg[IF_ID_IR[20:16]];

            ID_EX_NPC <= #2 IF_ID_NPC;
            ID_EX_IR  <= #2 IF_ID_IR;

            ID_EX_IMM <= #2 {{16{IF_ID_IR[15]}}, IF_ID_IR[15:0]};

            case(IF_ID_IR[31:26])
                ADD, SUB, ANDD, ORR, SLT, MUL:
                    ID_EX_type <= #2 RR_ALU;

                ADDI, SUBI, SLTI:
                    ID_EX_type <= #2 RM_ALU;

                LW:
                    ID_EX_type <= #2 LOAD;

                SW:
                    ID_EX_type <= #2 STORE;

                BEQZ, BNEQZ:
                    ID_EX_type <= #2 BRANCH;

                HLT:
                    ID_EX_type <= #2 HALT;

                default:
                    ID_EX_type <= #2 HALT;
            endcase
        end
    end

    //---------------------------------------------------------
    // 3. EXECUTION (EX) STAGE
    //---------------------------------------------------------
    always @(posedge clk1)
    begin
        if (!halted)
        begin
            // Pipeline Register Transfer
            EX_MEM_type <= #2 ID_EX_type;
            EX_MEM_IR   <= #2 ID_EX_IR;

            case (ID_EX_type)

            //-------------------------------------------------
            // Register-Register ALU Instructions
            //-------------------------------------------------
            RR_ALU:
            begin
                case (ID_EX_IR[31:26])
                    ADD:  EX_MEM_ALUOut <= #2 ID_EX_A + ID_EX_B;
                    SUB:  EX_MEM_ALUOut <= #2 ID_EX_A - ID_EX_B;
                    ANDD: EX_MEM_ALUOut <= #2 ID_EX_A & ID_EX_B;
                    ORR:  EX_MEM_ALUOut <= #2 ID_EX_A | ID_EX_B;
                    // Fixed: Used $signed() for accurate signed magnitude comparison
                    SLT:  EX_MEM_ALUOut <= #2 ($signed(ID_EX_A) < $signed(ID_EX_B)) ? 32'd1 : 32'd0;
                    MUL:  EX_MEM_ALUOut <= #2 ID_EX_A * ID_EX_B;
                    default: EX_MEM_ALUOut <= #2 32'd0;
                endcase
            end

            //-------------------------------------------------
            // Register-Immediate ALU Instructions
            //-------------------------------------------------
            RM_ALU:
            begin
                case (ID_EX_IR[31:26])
                    ADDI: EX_MEM_ALUOut <= #2 ID_EX_A + ID_EX_IMM;
                    SUBI: EX_MEM_ALUOut <= #2 ID_EX_A - ID_EX_IMM;
                    // Fixed: Used $signed() for accurate signed magnitude comparison
                    SLTI: EX_MEM_ALUOut <= #2 ($signed(ID_EX_A) < $signed(ID_EX_IMM)) ? 32'd1 : 32'd0;
                    default: EX_MEM_ALUOut <= #2 32'd0;
                endcase
            end

            //-------------------------------------------------
            // LOAD / STORE
            //-------------------------------------------------
            LOAD, STORE:
            begin
                EX_MEM_ALUOut <= #2 ID_EX_A + ID_EX_IMM;
                EX_MEM_B      <= #2 ID_EX_B;
            end

            //-------------------------------------------------
            // BRANCH
            //-------------------------------------------------
            BRANCH:
            begin
                // Compute branch target
                EX_MEM_ALUOut <= #2 ID_EX_NPC + ID_EX_IMM;
                // Branch condition (BEQZ/BNEQZ)
                EX_MEM_cond <= #2 (ID_EX_A == 32'd0);
            end

            //-------------------------------------------------
            // HALT
            //-------------------------------------------------
            HALT:
            begin
                EX_MEM_ALUOut <= #2 32'd0;
            end

            //-------------------------------------------------
            // Invalid Instruction
            //-------------------------------------------------
            default:
            begin
                EX_MEM_ALUOut <= #2 32'd0;
            end
            endcase
        end
    end

    //---------------------------------------------------------
    // 4. MEMORY ACCESS (MEM) STAGE
    //---------------------------------------------------------
    always @(posedge clk2)
    begin
        if (!halted)
        begin
            // Pass pipeline registers to WB stage
            MEM_WB_type   <= #2 EX_MEM_type;
            MEM_WB_IR     <= #2 EX_MEM_IR;
            MEM_WB_ALUOut <= #2 EX_MEM_ALUOut;

            case (EX_MEM_type)
            RR_ALU, RM_ALU:
            begin
                // No memory operation required
            end
            
            LOAD:
            begin
                MEM_WB_LMD <= #2 Mem[EX_MEM_ALUOut];
            end
            
            STORE:
            begin
                if (!taken_branch)
                    Mem[EX_MEM_ALUOut] <= #2 EX_MEM_B;
            end
            
            BRANCH, HALT:
            begin
            end
            default:
            begin
                // Nothing to access in memory
            end
            endcase
        end
    end

    //---------------------------------------------------------
    // 5. WRITE BACK (WB) STAGE
    //---------------------------------------------------------
    always @(posedge clk1)
    begin
        if(!taken_branch)
        begin
            case(MEM_WB_type)
            RR_ALU:
            begin
                if(MEM_WB_IR[15:11] != 0)
                    Reg[MEM_WB_IR[15:11]] <= #2 MEM_WB_ALUOut;
            end

            RM_ALU:
            begin
                if(MEM_WB_IR[20:16] != 0)
                    Reg[MEM_WB_IR[20:16]] <= #2 MEM_WB_ALUOut;
            end

            LOAD:
            begin
                if(MEM_WB_IR[20:16] != 0)
                    Reg[MEM_WB_IR[20:16]] <= #2 MEM_WB_LMD;
            end

            HALT:
            begin
                halted <= #2 1'b1;
            end
            endcase
        end
    end

endmodule

tb/mips32_tb.v
`timescale 1ns/1ps

module mips32_tb;

    // Testbench signals
    reg clk1;
    reg clk2;

    // Instantiate the Device Under Test (DUT)
    mips32 dut (
        .clk1(clk1),
        .clk2(clk2)
    );

    //---------------------------------------------------------
    // Clock Generation (2-Phase Non-Overlapping)
    //---------------------------------------------------------
    initial begin
        clk1 = 0;
        clk2 = 0;
        
        // Ensure initial block in DUT has time to execute (PC=0, Reg=0)
        #1; 
        
        forever begin
            #5 clk1 = 1; #5 clk1 = 0;
            #5 clk2 = 1; #5 clk2 = 0;
        end
    end

    //---------------------------------------------------------
    // Stimulus & Memory Initialization
    //---------------------------------------------------------
    initial begin
        // Wait a moment for DUT's internal "initial" block to zero out arrays
        #2;

        // Load a small test program into the DUT's Instruction Memory
        // -----------------------------------------------------------
        
        // Instruction 1: ADDI R1, R0, 5  (Opcode: 10, rs: 0, rt: 1, imm: 5)
        // Binary: 001010_00000_00001_0000000000000101 -> Hex: 32'h2801_0005
        dut.Mem[0] = 32'h2801_0005;

        // Instruction 2: ADDI R2, R0, 10 (Opcode: 10, rs: 0, rt: 2, imm: 10)
        // Binary: 001010_00000_00010_0000000000001010 -> Hex: 32'h2802_000A
        dut.Mem[1] = 32'h2802_000A;

        // --- NOPs INSerted to Resolve Data Hazard ---
        // NOP 1: ADD R0, R0, R0
        dut.Mem[2] = 32'h0000_0000;
        
        // NOP 2: ADD R0, R0, R0
        // These delay the pipeline enough for ADDI to reach Write-Back
        dut.Mem[3] = 32'h0000_0000;

        // Instruction 3: ADD R3, R1, R2  (Opcode: 0, rs: 1, rt: 2, rd: 3)
        // Binary: 000000_00001_00010_00011_00000000000 -> Hex: 32'h0022_1800
        dut.Mem[4] = 32'h0022_1800;

        // Instruction 4: HLT (Opcode: 63)
        // Binary: 111111_00000_00000_00000_00000000000 -> Hex: 32'hFC00_0000
        dut.Mem[5] = 32'hFC00_0000;

        // Monitor the PC and specific registers as the simulation runs
        $monitor("Time: %0t | PC: %0d | R1: %0d | R2: %0d | R3: %0d", 
                 $time, dut.PC, dut.Reg[1], dut.Reg[2], dut.Reg[3]);

        // Wait until the processor asserts the 'halted' flag
        wait (dut.halted == 1'b1);

        // Allow one extra cycle for the final Write-Back stage to finish
        #20;

        // Print final results
        $display("\n========================================");
        $display("   Pipeline Execution Completed");
        $display("========================================");
        $display("Final Register States:");
        $display("R1 = %0d (Expected: 5)", dut.Reg[1]);
        $display("R2 = %0d (Expected: 10)", dut.Reg[2]);
        $display("R3 = %0d (Expected: 15)", dut.Reg[3]);
        $display("========================================");

        // End simulation
        $finish;
    end

    initial begin
    $dumpfile("dump.vcd");
    $dumpvars(0, mips32_tb);
    end

endmodule

dump.vcd
$date
	Fri Jun 26 23:25:08 2026
$end
$version
	Icarus Verilog
$end
$timescale
	1ps
$end
$scope module mips32_tb $end
$var reg 1 ! clk1 $end
$var reg 1 " clk2 $end
$scope module dut $end
$var wire 1 ! clk1 $end
$var wire 1 " clk2 $end
$var parameter 6 # ADD $end
$var parameter 6 $ ADDI $end
$var parameter 6 % ANDD $end
$var parameter 6 & BEQZ $end
$var parameter 6 ' BNEQZ $end
$var parameter 3 ( BRANCH $end
$var parameter 3 ) HALT $end
$var parameter 6 * HLT $end
$var parameter 3 + LOAD $end
$var parameter 6 , LW $end
$var parameter 6 - MUL $end
$var parameter 6 . ORR $end
$var parameter 3 / RM_ALU $end
$var parameter 3 0 RR_ALU $end
$var parameter 6 1 SLT $end
$var parameter 6 2 SLTI $end
$var parameter 3 3 STORE $end
$var parameter 6 4 SUB $end
$var parameter 6 5 SUBI $end
$var parameter 6 6 SW $end
$var reg 32 7 EX_MEM_ALUOut [31:0] $end
$var reg 32 8 EX_MEM_B [31:0] $end
$var reg 32 9 EX_MEM_IR [31:0] $end
$var reg 1 : EX_MEM_cond $end
$var reg 3 ; EX_MEM_type [2:0] $end
$var reg 32 < ID_EX_A [31:0] $end
$var reg 32 = ID_EX_B [31:0] $end
$var reg 32 > ID_EX_IMM [31:0] $end
$var reg 32 ? ID_EX_IR [31:0] $end
$var reg 32 @ ID_EX_NPC [31:0] $end
$var reg 3 A ID_EX_type [2:0] $end
$var reg 32 B IF_ID_IR [31:0] $end
$var reg 32 C IF_ID_NPC [31:0] $end
$var reg 32 D MEM_WB_ALUOut [31:0] $end
$var reg 32 E MEM_WB_IR [31:0] $end
$var reg 32 F MEM_WB_LMD [31:0] $end
$var reg 3 G MEM_WB_type [2:0] $end
$var reg 32 H PC [31:0] $end
$var reg 1 I halted $end
$var reg 1 J taken_branch $end
$var integer 32 K i [31:0] $end
$upscope $end
$upscope $end
$enddefinitions $end
$comment Show the parameter values. $end
$dumpall
b1001 6
b1011 5
b1 4
b11 3
b1100 2
b100 1
b0 0
b1 /
b11 .
b101 -
b1000 ,
b10 +
b111111 *
b101 )
b100 (
b1101 '
b1110 &
b10 %
b1010 $
b0 #
$end
#0
$dumpvars
b10000000000 K
0J
0I
b0 H
b0 G
b0 F
b0 E
b0 D
b0 C
b0 B
b0 A
b0 @
b0 ?
b0 >
b0 =
b0 <
b0 ;
0:
b0 9
b0 8
b0 7
0"
0!
$end
#6000
1!
#8000
b1 H
b1 C
b101000000000010000000000000101 B
#11000
0!
#16000
1"
#18000
b1 A
b101 >
b101000000000010000000000000101 ?
b1 @
#21000
0"
#26000
1!
#28000
b101 7
b101000000000010000000000000101 9
b1 ;
b10 H
b10 C
b101000000000100000000000001010 B
#31000
0!
#36000
1"
#38000
b101 D
b101000000000010000000000000101 E
b1 G
b1010 >
b101000000000100000000000001010 ?
b10 @
#41000
0"
#46000
1!
#48000
b11 H
b11 C
b0 B
b1010 7
b101000000000100000000000001010 9
#51000
0!
#56000
1"
#58000
b0 A
b0 >
b0 ?
b11 @
b1010 D
b101000000000100000000000001010 E
#61000
0"
#66000
1!
#68000
b0 7
b0 9
b0 ;
b100 H
b100 C
#71000
0!
#76000
1"
#78000
b0 D
b0 E
b0 G
b100 @
#81000
0"
#86000
1!
#88000
b101 H
b101 C
b1000100001100000000000 B
#91000
0!
#96000
1"
#98000
b1100000000000 >
b1000100001100000000000 ?
b101 @
b1010 =
b101 <
#101000
0"
#106000
1!
#108000
b1111 7
b1000100001100000000000 9
b110 H
b110 C
b11111100000000000000000000000000 B
#111000
0!
#116000
1"
#118000
b1111 D
b1000100001100000000000 E
b101 A
b0 >
b11111100000000000000000000000000 ?
b110 @
b0 =
b0 <
#121000
0"
#126000
1!
#128000
b111 H
b111 C
b0 B
b0 7
b11111100000000000000000000000000 9
b101 ;
#131000
0!
#136000
1"
#138000
b0 A
b0 ?
b111 @
b0 D
b11111100000000000000000000000000 E
b101 G
#141000
0"
#146000
1!
#148000
1I
b0 9
b0 ;
b1000 H
b1000 C
